{
  "expenses": [
    {
      "id": "bae8",
      "date": "2024-06-17",
      "category": "Food/Drinks",
      "amount": 123,
      "comment": "Credit"
    },
    {
      "id": "2379",
      "date": "2024-06-17",
      "category": "Food/Drinks",
      "amount": 100,
      "comment": "Credit"
    },
    {
      "id": "f96b",
      "date": "2024-06-12",
      "category": "Shopping",
      "amount": 100,
      "comment": "Credit"
    },
    {
      "id": "d94e",
      "date": "2024-06-12",
      "category": "Shopping",
      "amount": 200,
      "comment": "Credit"
    },
    {
      "id": "c616",
      "date": "2024-06-16",
      "category": "Family",
      "amount": 15,
      "comment": "Credit"
    },
    {
      "id": "20d8",
      "date": "2024-05-12",
      "category": "Health/Sport",
      "amount": 150,
      "comment": "Debit"
    },
    {
      "id": "13e7",
      "date": "2024-05-12",
      "category": "Health/Sport",
      "amount": 200,
      "comment": "Debit"
    },
    {
      "id": "c5df",
      "date": "2024-05-31",
      "category": "Travelser",
      "amount": 120,
      "comment": "Credit"
    },
    {
      "id": "00e3",
      "date": "2024-06-04",
      "category": "Other (Expenses)",
      "amount": 123,
      "comment": "Credit"
    },
    {
      "id": "bf2a",
      "date": "2024-05-09",
      "category": "Travelser",
      "amount": 123,
      "comment": "Debit"
    },
    {
      "id": "9839",
      "date": "2024-06-05",
      "category": "Travelser",
      "amount": 1000,
      "comment": "Credit"
    },
    {
      "id": "530b",
      "date": "2024-06-01",
      "category": "Travelser",
      "amount": 100,
      "comment": "Credit"
    }
  ],
  "PaymentType": [
    {
      "id": "1",
      "name": "Credit",
      "balnce": 19061
    },
    {
      "id": "2",
      "name": "Debit",
      "balnce": 773
    },
    {
      "id": "3",
      "name": "Cash",
      "balnce": 302
    }
  ],
  "income": [
    {
      "id": "e42b",
      "date": "2024-06-12",
      "accountType": "Debit",
      "amount": 1000
    },
    {
      "id": "4240",
      "date": "2024-06-12",
      "accountType": "Debit",
      "amount": 100
    },
    {
      "id": "1b2d",
      "date": "2024-05-31",
      "accountType": "Credit",
      "amount": 112
    },
    {
      "id": "e06b",
      "date": "2024-06-05",
      "accountType": "Credit",
      "amount": 100
    },
    {
      "id": "8d6f",
      "date": "2024-06-01",
      "accountType": "Debit",
      "amount": 123
    },
    {
      "id": "03b3",
      "date": "2024-06-02",
      "accountType": "Debit",
      "amount": 123
    },
    {
      "id": "8b94",
      "date": "2024-06-01",
      "accountType": "Cash",
      "amount": 200
    }
  ],
  "categories": [
    {
      "id": "1",
      "name": "Income",
      "type": "income",
      "isOpen": true
    },
    {
      "id": "2",
      "name": "Expenses",
      "type": "expense",
      "isOpen": true
    }
  ],
  "subcategories": [
    {
      "id": "29",
      "name": "Travelser",
      "categoryId": "2"
    },
    {
      "id": "30",
      "name": "Other (Expenses)",
      "categoryId": "2"
    },
    {
      "id": "3c1a",
      "name": "asaa",
      "categoryId": "1"
    }
  ]
}